warc/__init__.py
warc/arc.py
warc/utils.py
warc/warc.py
warc3_wet-0.2.4.dist-info/LICENSE
warc3_wet-0.2.4.dist-info/METADATA
warc3_wet-0.2.4.dist-info/WHEEL
warc3_wet-0.2.4.dist-info/top_level.txt
warc3_wet-0.2.4.dist-info/RECORD
