Metadata-Version: 2.1
Name: warc3-wet
Version: 0.2.4
Summary: Python library to work with ARC and WARC files
Home-page: https://github.com/Willian-Zhang/warc3
Author: Anand Chitipothu, Noufal Ibrahim, Ryan Chartier, Jan Pieter Bruins Slot, Almer S. Tigelaar, Willian Zhang
Author-email: info@archive.org
License: GPLv2
Platform: any
Classifier: Development Status :: 4 - Beta
Classifier: Environment :: Web Environment
Classifier: Intended Audience :: Developers
Classifier: License :: OSI Approved :: GNU General Public License v2 (GPLv2)
Classifier: Operating System :: OS Independent
Classifier: Programming Language :: Python
License-File: LICENSE
